thepeer/__init__.py
thepeer/main.py
thepeer/utils/__init__.py
thepeer/utils/constants.py
thepeer/utils/exceptions/__init__.py
thepeer/utils/exceptions/handleErrors.py
thepeer/utils/exceptions/types/__init__.py
thepeer/utils/exceptions/types/base.py
thepeer/utils/exceptions/types/forbidden.py
thepeer/utils/exceptions/types/notacceptable.py
thepeer/utils/exceptions/types/notfound.py
thepeer/utils/exceptions/types/servererror.py
thepeer/utils/exceptions/types/serviceunavailable.py
thepeer/utils/exceptions/types/unauthorized.py
thepeer/utils/exceptions/types/unprocessableentity.py
pythepeer-0.0.6.dist-info/METADATA
pythepeer-0.0.6.dist-info/WHEEL
pythepeer-0.0.6.dist-info/top_level.txt
pythepeer-0.0.6.dist-info/RECORD
