Metadata-Version: 2.1
Name: pythepeer
Version: 0.0.6
Summary: official python sdk for interacting with thepeer payment processing     infrastructure
Home-page: https://github.com/thepeerstack/python-sdk
Author: Osagie Iyayi
Author-email: iyayiemmanuel1@gmail.com
License: MIT
Keywords: python,fintech,peer-to-peer
Classifier: Development Status :: 5 - Production/Stable
Classifier: Intended Audience :: Developers
Classifier: Topic :: Software Development :: Build Tools
Classifier: License :: OSI Approved :: MIT License
Classifier: Programming Language :: Python :: 3
Classifier: Programming Language :: Python :: 3.6
Classifier: Programming Language :: Python :: 3.7
Classifier: Programming Language :: Python :: 3.8
Classifier: Programming Language :: Python :: 3.9
Classifier: Programming Language :: Python :: 3.10
Classifier: Programming Language :: Python :: 3.11
Classifier: Topic :: Software Development :: Libraries
Requires-Dist: httpx
